.mina/ariadne.toml
arclet/alconna/ariadne/__init__.py
arclet/alconna/ariadne/adapter.py
arclet/alconna/ariadne/typings.py
arclet_alconna_ariadne-0.18.3.dist-info/METADATA
arclet_alconna_ariadne-0.18.3.dist-info/WHEEL
arclet_alconna_ariadne-0.18.3.dist-info/licenses/LICENSE
arclet_alconna_ariadne-0.18.3.dist-info/RECORD
