Metadata-Version: 2.1
Name: arclet-alconna-ariadne
Version: 0.18.3
Summary: Support Alconna to GraiaProject/Ariadne
Keywords: alconna,graia,arclet
Home-page: https://github.com/ArcletProject/Alconna-Graia
Author-Email: RF-Tar-Railt <rf_tar_railt@qq.com>
License: AGPL-3.0
Classifier: Development Status :: 4 - Beta
Classifier: License :: OSI Approved :: GNU Affero General Public License v3
Classifier: Operating System :: OS Independent
Classifier: Programming Language :: Python :: 3.10
Classifier: Programming Language :: Python :: 3.8
Classifier: Programming Language :: Python :: 3.9
Project-URL: Homepage, https://github.com/ArcletProject/Alconna-Graia
Project-URL: Repository, https://github.com/ArcletProject/Alconna-Graia
Requires-Python: >=3.8
Requires-Dist: arclet-alconna-graia<0.19.0,>=0.18.3
Requires-Dist: graia-ariadne<1.0.0,>=0.11.0
